Metadata-Version: 2.1
Name: Matplot3DEx
Version: 0.1
Summary: A Matplotlib 3D Extension package for enhanced data visualization
Home-page: https://github.com/ishanoshada/matplot3dex
Author: Ishan Oshada
Author-email: ishan.kodithuwakku@gmail.com
License: UNKNOWN
Platform: UNKNOWN
Classifier: Development Status :: 3 - Alpha
Classifier: Intended Audience :: Developers
Classifier: License :: OSI Approved :: MIT License
Classifier: Programming Language :: Python :: 3
Classifier: Programming Language :: Python :: 3.6
Classifier: Programming Language :: Python :: 3.7
Classifier: Programming Language :: Python :: 3.8
